donnedessousmtr/__init__.py
donnedessousmtr/main.py
donnedessousmtr-0.1.0.dist-info/METADATA
donnedessousmtr-0.1.0.dist-info/WHEEL
donnedessousmtr-0.1.0.dist-info/RECORD
